Metadata-Version: 2.1
Name: byte-words
Version: 1.1.0
Summary: Turn binary files into words and vice versa
Home-page: https://github.com/jbaber/byte-words
Author: John Baber-Lucero
Author-email: pypi@frundle.com
License: GPLv3
Platform: UNKNOWN
License-File: LICENSE
